[
 {
  "table":"DD04L",
  "data":
  [
   {
    "ROLLNAME":"Z_PR_APPROVE",
    "AS4LOCAL":"L",
    "AS4VERS":0,
    "DOMNAME":"",
    "ROUTPUTLEN":0,
    "MEMORYID":"",
    "LOGFLAG":"",
    "HEADLEN":55,
    "SCRLEN1":10,
    "SCRLEN2":20,
    "SCRLEN3":40,
    "ACTFLAG":"",
    "APPLCLASS":"",
    "AUTHCLASS":0,
    "AS4USER":"ADGUPTA",
    "AS4DATE":"2021-12-02",
    "AS4TIME":"04:40:45",
    "DTELMASTER":"E",
    "RESERVEDTE":"",
    "DTELGLOBAL":"",
    "SHLPNAME":"",
    "SHLPFIELD":"",
    "DEFFDNAME":"",
    "DATATYPE":"CHAR",
    "LENG":3,
    "DECIMALS":0,
    "OUTPUTLEN":3,
    "LOWERCASE":"",
    "SIGNFLAG":"",
    "CONVEXIT":"",
    "VALEXI":"",
    "ENTITYTAB":"",
    "REFKIND":"",
    "REFTYPE":"",
    "PROXYTYPE":"",
    "LTRFLDDIS":"",
    "BIDICTRLC":"",
    "NOHISTORY":"",
    "ABAP_LANGUAGE_VERSION":""
   }
  ]
 },
 {
  "table":"DD04T",
  "data":
  [
   {
    "ROLLNAME":"Z_PR_APPROVE",
    "DDLANGUAGE":"E",
    "AS4LOCAL":"N",
    "AS4VERS":0,
    "DDTEXT":"Approve Purchase Requisition",
    "REPTEXT":"Approve Purchase Requisition",
    "SCRTEXT_S":"Appr Pr",
    "SCRTEXT_M":"Approve Pur Req",
    "SCRTEXT_L":"Approve Purchase Requisition"
   }
  ]
 },
 {
  "table":"DDTYPES",
  "data":
  [
   {
    "TYPENAME":"Z_PR_APPROVE",
    "STATE":"N",
    "TYPEKIND":"DTEL"
   }
  ]
 },
 {
  "table":"TADIR",
  "data":
  [
   {
    "PGMID":"R3TR",
    "OBJECT":"DTEL",
    "OBJ_NAME":"Z_PR_APPROVE",
    "KORRNUM":"",
    "SRCSYSTEM":"...",
    "AUTHOR":"ADGUPTA",
    "SRCDEP":"",
    "DEVCLASS":"Z001",
    "GENFLAG":"",
    "EDTFLAG":"",
    "CPROJECT":" S",
    "MASTERLANG":"E",
    "VERSID":"",
    "PAKNOCHECK":"",
    "OBJSTABLTY":"",
    "COMPONENT":"",
    "CRELEASE":"",
    "DELFLAG":"",
    "TRANSLTTXT":"",
    "CREATED_ON":"2021-12-02",
    "CHECK_DATE":"2021-12-02",
    "CHECK_CFG":""
   }
  ]
 }
]