[
 {
  "table":"DD02L",
  "data":
  [
   {
    "TABNAME":"ZWYHEALTH",
    "AS4LOCAL":"L",
    "AS4VERS":0,
    "TABCLASS":"TRANSP",
    "SQLTAB":"",
    "DATMIN":0,
    "DATMAX":0,
    "DATAVG":0,
    "CLIDEP":"X",
    "BUFFERED":"",
    "COMPRFLAG":"",
    "LANGDEP":"",
    "ACTFLAG":"",
    "APPLCLASS":"",
    "AUTHCLASS":0,
    "AS4USER":"JANGWY",
    "AS4DATE":"2022-01-27",
    "AS4TIME":"11:57:24",
    "MASTERLANG":"",
    "MAINFLAG":"X",
    "CONTFLAG":"C",
    "RESERVETAB":"",
    "GLOBALFLAG":"",
    "PROZPUFF":0,
    "VIEWCLASS":"",
    "VIEWGRANT":"",
    "MULTIPLEX":"",
    "SHLPEXI":"",
    "PROXYTYPE":"",
    "EXCLASS":3,
    "WRONGCL":"",
    "ALWAYSTRP":"",
    "ALLDATAINCL":"",
    "WITH_PARAMETERS":"",
    "EXVIEW_INCLUDED":"",
    "KEYMAX_FEATURE":"",
    "KEYLEN_FEATURE":"",
    "TABLEN_FEATURE":"",
    "NONTRP_INCLUDED":"",
    "VIEWREF":"",
    "VIEWREF_ERR":"",
    "VIEWREF_POS_CHG":"",
    "TBFUNC_INCLUDED":"",
    "IS_GTT":"",
    "SESSION_VAR_EX":"",
    "FROM_ENTITY":"",
    "PK_IS_INVHASH":"",
    "USED_SESSION_VARS":"",
    "ABAP_LANGUAGE_VERSION":"",
    "HDB_ONLY_ENTITY_INCLUDED":""
   }
  ]
 },
 {
  "table":"DD02T",
  "data":
  [
   {
    "TABNAME":"ZWYHEALTH",
    "DDLANGUAGE":"E",
    "AS4LOCAL":"N",
    "AS4VERS":0,
    "DDTEXT":"Employees Health Plans"
   }
  ]
 },
 {
  "table":"DD03L",
  "data":
  [
   {
    "TABNAME":"ZWYHEALTH",
    "FIELDNAME":"ANN_PREM",
    "AS4LOCAL":"N",
    "AS4VERS":0,
    "POSITION":4,
    "KEYFLAG":"",
    "MANDATORY":"",
    "ROLLNAME":"ZWYANNPREM",
    "CHECKTABLE":"",
    "ADMINFIELD":"0",
    "INTTYPE":"P",
    "INTLEN":4,
    "REFTABLE":"",
    "PRECFIELD":"",
    "REFFIELD":"",
    "CONROUT":"",
    "NOTNULL":"",
    "DATATYPE":"DEC",
    "LENG":6,
    "DECIMALS":0,
    "DOMNAME":"ZWYANNPREM",
    "SHLPORIGIN":"",
    "TABLETYPE":"",
    "DEPTH":0,
    "COMPTYPE":"E",
    "REFTYPE":"",
    "LANGUFLAG":"",
    "DBPOSITION":0,
    "ANONYMOUS":"",
    "OUTPUTSTYLE":0,
    "SRS_ID":0
   },
   {
    "TABNAME":"ZWYHEALTH",
    "FIELDNAME":"DESCR",
    "AS4LOCAL":"N",
    "AS4VERS":0,
    "POSITION":3,
    "KEYFLAG":"",
    "MANDATORY":"",
    "ROLLNAME":"ZWYDESCR",
    "CHECKTABLE":"",
    "ADMINFIELD":"0",
    "INTTYPE":"C",
    "INTLEN":160,
    "REFTABLE":"",
    "PRECFIELD":"",
    "REFFIELD":"",
    "CONROUT":"",
    "NOTNULL":"",
    "DATATYPE":"CHAR",
    "LENG":80,
    "DECIMALS":0,
    "DOMNAME":"ZWYDESCR",
    "SHLPORIGIN":"",
    "TABLETYPE":"",
    "DEPTH":0,
    "COMPTYPE":"E",
    "REFTYPE":"",
    "LANGUFLAG":"",
    "DBPOSITION":0,
    "ANONYMOUS":"",
    "OUTPUTSTYLE":0,
    "SRS_ID":0
   },
   {
    "TABNAME":"ZWYHEALTH",
    "FIELDNAME":"MANDT",
    "AS4LOCAL":"N",
    "AS4VERS":0,
    "POSITION":1,
    "KEYFLAG":"X",
    "MANDATORY":"",
    "ROLLNAME":"MANDT",
    "CHECKTABLE":"",
    "ADMINFIELD":"0",
    "INTTYPE":"C",
    "INTLEN":6,
    "REFTABLE":"",
    "PRECFIELD":"",
    "REFFIELD":"",
    "CONROUT":"",
    "NOTNULL":"X",
    "DATATYPE":"CLNT",
    "LENG":3,
    "DECIMALS":0,
    "DOMNAME":"MANDT",
    "SHLPORIGIN":"",
    "TABLETYPE":"",
    "DEPTH":0,
    "COMPTYPE":"E",
    "REFTYPE":"",
    "LANGUFLAG":"",
    "DBPOSITION":0,
    "ANONYMOUS":"",
    "OUTPUTSTYLE":0,
    "SRS_ID":0
   },
   {
    "TABNAME":"ZWYHEALTH",
    "FIELDNAME":"PLAN_ID",
    "AS4LOCAL":"N",
    "AS4VERS":0,
    "POSITION":2,
    "KEYFLAG":"X",
    "MANDATORY":"",
    "ROLLNAME":"ZWYHLTHPLN",
    "CHECKTABLE":"",
    "ADMINFIELD":"0",
    "INTTYPE":"N",
    "INTLEN":8,
    "REFTABLE":"",
    "PRECFIELD":"",
    "REFFIELD":"",
    "CONROUT":"",
    "NOTNULL":"X",
    "DATATYPE":"NUMC",
    "LENG":4,
    "DECIMALS":0,
    "DOMNAME":"ZWYHLTHPLN",
    "SHLPORIGIN":"",
    "TABLETYPE":"",
    "DEPTH":0,
    "COMPTYPE":"E",
    "REFTYPE":"",
    "LANGUFLAG":"",
    "DBPOSITION":0,
    "ANONYMOUS":"",
    "OUTPUTSTYLE":0,
    "SRS_ID":0
   }
  ]
 },
 {
  "table":"DD09L",
  "data":
  [
   {
    "TABNAME":"ZWYHEALTH",
    "AS4LOCAL":"N",
    "AS4VERS":0,
    "TABKAT":"0",
    "TABART":"USER",
    "PUFFERUNG":"",
    "SCHFELDANZ":0,
    "PROTOKOLL":"",
    "SPEICHPUFF":"",
    "AS4USER":"JANGWY",
    "AS4DATE":"2022-01-27",
    "AS4TIME":"11:57:24",
    "TRANSPFLAG":"",
    "RESERVE":"",
    "UEBERSETZ":"",
    "ACTFLAG":"",
    "BUFALLOW":"N",
    "JAVAONLY":"",
    "ROWORCOLST":"C",
    "SHARINGTYPE":"",
    "LOAD_UNIT":""
   }
  ]
 },
 {
  "table":"DDTYPES",
  "data":
  [
   {
    "TYPENAME":"ZWYHEALTH",
    "STATE":"N",
    "TYPEKIND":"TABL"
   }
  ]
 },
 {
  "table":"TADIR",
  "data":
  [
   {
    "PGMID":"R3TR",
    "OBJECT":"TABL",
    "OBJ_NAME":"ZWYHEALTH",
    "KORRNUM":"",
    "SRCSYSTEM":"...",
    "AUTHOR":"JANGWY",
    "SRCDEP":"",
    "DEVCLASS":"YWYTRAINING",
    "GENFLAG":"",
    "EDTFLAG":"",
    "CPROJECT":" S",
    "MASTERLANG":"E",
    "VERSID":"",
    "PAKNOCHECK":"",
    "OBJSTABLTY":"",
    "COMPONENT":"",
    "CRELEASE":"",
    "DELFLAG":"",
    "TRANSLTTXT":"",
    "CREATED_ON":"2022-01-27",
    "CHECK_DATE":"2022-01-27",
    "CHECK_CFG":""
   }
  ]
 }
]